modelscope_tts/ModelscopeTTS.py
modelscope_tts/__init__.py
modelscope_tts-0.1.5.dist-info/LICENSE
modelscope_tts-0.1.5.dist-info/METADATA
modelscope_tts-0.1.5.dist-info/WHEEL
modelscope_tts-0.1.5.dist-info/top_level.txt
modelscope_tts-0.1.5.dist-info/RECORD
