Metadata-Version: 2.1
Name: modelscope_tts
Version: 0.1.5
Summary: modelscopeTTS Unofficial api,see https://github.com/avilliai/modelscopeTTS for more information
Home-page: https://github.com/avilliai/modelscopeTTS
Author: avillia
Author-email: larea06@gmail.com
License-File: LICENSE
Requires-Dist: httpx
